lap_reg/LazyPolynomialRegression.py
lap_reg/Model.py
lap_reg/PolynomialColumnsAdder.py
lap_reg/PowerDecider.py
lap_reg/__init__.py
lap_reg/alreadyInitialized.py
lap_reg-0.0.1.dist-info/LICENSE
lap_reg-0.0.1.dist-info/METADATA
lap_reg-0.0.1.dist-info/WHEEL
lap_reg-0.0.1.dist-info/top_level.txt
lap_reg-0.0.1.dist-info/RECORD
